{"methods":[],"package":"android.provider","constants":["String ISPRIMARY This constant was deprecated in API level 5. see ContactsContract","String LABEL This constant was deprecated in API level 5. see ContactsContract","String NUMBER This constant was deprecated in API level 5. see ContactsContract","String NUMBER_KEY This constant was deprecated in API level 5. see ContactsContract","String TYPE This constant was deprecated in API level 5. see ContactsContract","int TYPE_CUSTOM This constant was deprecated in API level 5. see ContactsContract","int TYPE_FAX_HOME This constant was deprecated in API level 5. see ContactsContract","int TYPE_FAX_WORK This constant was deprecated in API level 5. see ContactsContract","int TYPE_HOME This constant was deprecated in API level 5. see ContactsContract","int TYPE_MOBILE This constant was deprecated in API level 5. see ContactsContract","int TYPE_OTHER This constant was deprecated in API level 5. see ContactsContract","int TYPE_PAGER This constant was deprecated in API level 5. see ContactsContract","int TYPE_WORK This constant was deprecated in API level 5. see ContactsContract"],"class":"Contacts.PhonesColumns","constructors":[],"fields":[]}